fastoauth/__init__.py
fastoauth/_redis.py
fastoauth/oauth.py
fastoauth/sample/__init__.py
fastoauth/sample/oauth_server.py
fastoauth/schemas.py
fastoauth/test/__init__.py
fastoauth/test/test_oauth2.py
fastoauth/util/__init__.py
fastoauth/util/singleton.py
README.MD
README_zh.MD
fastoauth-0.1.10.dist-info/METADATA
fastoauth-0.1.10.dist-info/WHEEL
fastoauth-0.1.10.dist-info/RECORD
