Metadata-Version: 2.1
Name: fastoauth
Version: 0.1.10
Summary: 
License: MIT
Author: taohoo
Author-email: taohoo@163.com
Requires-Python: >=3.10
Classifier: License :: OSI Approved :: MIT License
Classifier: Programming Language :: Python :: 3
Classifier: Programming Language :: Python :: 3.10
Classifier: Programming Language :: Python :: 3.11
Classifier: Programming Language :: Python :: 3.12
Requires-Dist: fastapi (>=0.100.0)
Requires-Dist: pydantic (>=1.10.10)
Requires-Dist: pyopenssl (>=24.0.0)
Requires-Dist: python-jose (>=3.3.0)
Requires-Dist: python-multipart (>=0.0.9)
Requires-Dist: redis (>=5.0.5)
Requires-Dist: uvicorn (>=0.30.0)
